TracDocs-0.3.dist-info/DESCRIPTION.rst
TracDocs-0.3.dist-info/METADATA
TracDocs-0.3.dist-info/RECORD
TracDocs-0.3.dist-info/WHEEL
TracDocs-0.3.dist-info/dependency_links.txt
TracDocs-0.3.dist-info/entry_points.txt
TracDocs-0.3.dist-info/metadata.json
TracDocs-0.3.dist-info/top_level.txt
tracdocs/__init__.py
tracdocs/web_ui.py
tracdocs/htdocs/common.css
tracdocs/htdocs/docutils.css
tracdocs/htdocs/prettify.css
tracdocs/htdocs/prettify.js
tracdocs/htdocs/prettify.min.js
tracdocs/templates/docs.html
