Metadata-Version: 2.0
Name: TracDocs
Version: 0.3
Summary: A Trac plugin for RCS-backed documentation
Home-page: http://github.com/mrjbq7/tracdocs
Author: John Benediktsson
Author-email: mrjbq7@gmail.com
License: UNKNOWN
Download-URL: http://github.com/mrjbq7/tracdocs/zipball/master#egg=TracDocs-0.3
Platform: UNKNOWN
Classifier: Development Status :: 4 - Beta
Classifier: Framework :: Trac
Classifier: License :: OSI Approved :: BSD License
